landingzones/__init__.py
landingzones/check_deployment_readiness.py
landingzones/config.py
landingzones/generate_cron_files.py
landingzones/config/config.yaml.example
landingzones-1.0.4.dist-info/METADATA
landingzones-1.0.4.dist-info/WHEEL
landingzones-1.0.4.dist-info/entry_points.txt
landingzones-1.0.4.dist-info/RECORD
