Metadata-Version: 2.4
Name: landingzones
Version: 1.0.4
Summary: Automated data transfer system using rsync and cron
Project-URL: Homepage, https://github.com/ssi-dk/landingzones
Project-URL: Repository, https://github.com/ssi-dk/landingzones
Author: SSI-DK
License-Expression: MIT
Keywords: automation,cron,data-transfer,rsync
Classifier: Development Status :: 4 - Beta
Classifier: Intended Audience :: System Administrators
Classifier: Programming Language :: Python :: 3
Classifier: Programming Language :: Python :: 3.8
Classifier: Programming Language :: Python :: 3.9
Classifier: Programming Language :: Python :: 3.10
Classifier: Programming Language :: Python :: 3.11
Classifier: Programming Language :: Python :: 3.12
Classifier: Topic :: System :: Systems Administration
Requires-Python: >=3.8
Requires-Dist: pandas>=1.0.0
Requires-Dist: pyyaml>=5.0.0
Provides-Extra: dev
Requires-Dist: black; extra == 'dev'
Requires-Dist: flake8; extra == 'dev'
Requires-Dist: pytest-cov>=4.0.0; extra == 'dev'
Requires-Dist: pytest>=7.0.0; extra == 'dev'
Provides-Extra: test
Requires-Dist: pytest-cov>=4.0.0; extra == 'test'
Requires-Dist: pytest>=7.0.0; extra == 'test'
